videolab/__init__.py
videolab/cli.py
videolab/utils.py
videolab/commands/__init__.py
videolab/commands/env.py
videolab/commands/scrub.py
videolab/commands/watermark.py
videolab-0.5.16.dist-info/licenses/LICENSE.md
videolab-0.5.16.dist-info/METADATA
videolab-0.5.16.dist-info/WHEEL
videolab-0.5.16.dist-info/entry_points.txt
videolab-0.5.16.dist-info/top_level.txt
videolab-0.5.16.dist-info/RECORD
