Metadata-Version: 2.4
Name: videolab
Version: 0.5.16
Summary: A CLI for video processing.
Author: Kian-Meng Ang
License: AGPL-3.0-or-later
Classifier: Programming Language :: Python
Classifier: Programming Language :: Python :: 3
Classifier: Programming Language :: Python :: 3.10
Classifier: Programming Language :: Python :: 3.11
Classifier: Programming Language :: Python :: 3.12
Classifier: Programming Language :: Python :: 3.13
Classifier: Programming Language :: Python :: 3.14
Requires-Python: >=3.10
License-File: LICENSE.md
Requires-Dist: av<16.0.0,>=15.1.0
Requires-Dist: Pillow>=10.4.0
Requires-Dist: numpy>=1.26.0
Requires-Dist: tqdm>=4.66.0
Provides-Extra: dev
Requires-Dist: nox; extra == "dev"
Provides-Extra: test
Requires-Dist: pytest; extra == "test"
Requires-Dist: pytest-cov; extra == "test"
Requires-Dist: pytest-randomly; extra == "test"
Requires-Dist: pytest-xdist; extra == "test"
Requires-Dist: pytest-mock; extra == "test"
Provides-Extra: lint
Requires-Dist: mypy; extra == "lint"
Requires-Dist: pre-commit; extra == "lint"
Provides-Extra: doc
Requires-Dist: furo; extra == "doc"
Requires-Dist: myst-parser; extra == "doc"
Requires-Dist: sphinx; extra == "doc"
Requires-Dist: sphinx-autobuild; extra == "doc"
Requires-Dist: sphinx-autodoc-typehints; extra == "doc"
Requires-Dist: sphinx-copybutton; extra == "doc"
Dynamic: license-file
